idea_generator/__init__.py
idea_generator/generator.py
tests/__init__.py
tests/test_generator.py
infinite_idealist-0.1.2.dist-info/METADATA
infinite_idealist-0.1.2.dist-info/WHEEL
infinite_idealist-0.1.2.dist-info/top_level.txt
infinite_idealist-0.1.2.dist-info/RECORD
