Metadata-Version: 2.1
Name: infinite_idealist
Version: 0.1.2
Summary: A flexible Python library for generating and refining creative ideas using LLMs and embeddings.
Home-page: https://github.com/yoheinakajima/infinite-idealist
Author: Yohei Nakajima
Author-email: Yohei Nakajima <yohei@example.com>
License: MIT
Classifier: Programming Language :: Python :: 3
Classifier: License :: OSI Approved :: MIT License
Classifier: Operating System :: OS Independent
Requires-Python: >=3.7
Requires-Dist: litellm>=0.2.0
Requires-Dist: pydantic>=1.8.2
Requires-Dist: scikit-learn>=0.24.2
Requires-Dist: numpy>=1.21.0
